mappy.cpython-310-aarch64-linux-gnu.so
ont_mappy-2.28.dist-info/top_level.txt
ont_mappy-2.28.dist-info/METADATA
ont_mappy-2.28.dist-info/RECORD
ont_mappy-2.28.dist-info/WHEEL
ont_mappy-2.28.dist-info/LICENSE.txt
ont_mappy-2.28.data/scripts/minimap2.py
