Metadata-Version: 2.1
Name: ont-mappy
Version: 2.28
Summary: Minimap2 python binding
Home-page: https://github.com/lh3/minimap2
Author: Heng Li
Author-email: lh3@me.com
License: MIT
Keywords: sequence-alignment
Classifier: Development Status :: 5 - Production/Stable
Classifier: License :: OSI Approved :: MIT License
Classifier: Operating System :: POSIX
Classifier: Programming Language :: C
Classifier: Programming Language :: Cython
Classifier: Programming Language :: Python :: 2.7
Classifier: Programming Language :: Python :: 3
Classifier: Intended Audience :: Science/Research
Classifier: Topic :: Scientific/Engineering :: Bio-Informatics
License-File: LICENSE.txt
